[
  {
    "id": 1,
    "title": "10 Essential Web Development Tools Every Developer Should Know",
    "author_img": "https://i.ibb.co/0Yk5j5t/boy1.png",
    "author_name": "John Doe",
    "posted_date": "2023-09-12",
    "reading_time": 10,
    "hashtags": ["technology", "coding", "webdev"],
    "cover_img": "https://i.ibb.co/zG3GMpk/1.jpg"
  },
  {
    "id": 2,
    "title": "Mastering Responsive Web Design: Tips and Best Practices",
    "author_img": "https://i.ibb.co/cLxB8Yp/boy2.jpg",
    "author_name": "Jane Smith",
    "posted_date": "2023-09-11",
    "reading_time": 8,
    "hashtags": ["travel", "adventure"],
    "cover_img": "https://i.ibb.co/0mGrwDT/2.png"
  },
  {
    "id": 3,
    "title": "The Latest Trends in Web Development: What's Hot in 2023",
    "author_img": "https://i.ibb.co/Qr0xKNb/girl1.jpg",
    "author_name": "David Johnson",
    "posted_date": "2023-09-10",
    "reading_time": 15,
    "hashtags": ["food", "cooking", "recipes"],
    "cover_img": "https://i.ibb.co/LzD1Lqy/3.png"
  },
  {
    "id": 4,
    "title": "Optimizing Website Performance: Strategies for Faster Load Times",
    "author_img": "https://i.ibb.co/YQXhGkZ/girl2.jpg",
    "author_name": "Emily Wilson",
    "posted_date": "2023-09-09",
    "reading_time": 12,
    "hashtags": ["fitness", "health", "exercise"],
    "cover_img": "https://i.ibb.co/XFYs5zw/4.jpg"
  },
  {
    "id": 5,
    "title": "Exploring Creative Web Design: Inspiring Artistic Websites",
    "author_img": "https://i.ibb.co/ynGRHr2/profile.png",
    "author_name": "Michaela Brown",
    "posted_date": "2023-09-08",
    "reading_time": 7,
    "hashtags": ["art", "painting"],
    "cover_img": "https://i.ibb.co/zG3GMpk/1.jpg"
  }
]
